{
    "bezirk":"06",
    "data":
        [
            {
                "lng":6.86738760257137,
                "lat":51.268442857568
            },
            {
                "lng":6.86559476914061,
                "lat":51.2703069779304
            },
            {
                "lng":6.86540579826225,
                "lat":51.2710248045969
            },
            {
                "lng":6.86591866910987,
                "lat":51.2724471160281
            },
            {
                "lng":6.86312416818712,
                "lat":51.2734447586782
            },
            {
                "lng":6.86151604992262,
                "lat":51.2736421995037
            },
            {
                "lng":6.85971696662176,
                "lat":51.2743572057427
            },
            {
                "lng":6.85832560876186,
                "lat":51.2742553081797
            },
            {
                "lng":6.8563548083482,
                "lat":51.2752139005607
            },
            {
                "lng":6.85324749644377,
                "lat":51.2756547309793
            },
            {
                "lng":6.85139025263077,
                "lat":51.2761551290125
            },
            {
                "lng":6.85076990242053,
                "lat":51.2768321865436
            },
            {
                "lng":6.85116302632049,
                "lat":51.2785812550282
            },
            {
                "lng":6.84835651475975,
                "lat":51.2778265849201
            },
            {
                "lng":6.84352581538443,
                "lat":51.2766688927865
            },
            {
                "lng":6.84195522760632,
                "lat":51.2761653578274
            },
            {
                "lng":6.84025213230532,
                "lat":51.2766991798406
            },
            {
                "lng":6.83912999004217,
                "lat":51.2762680948354
            },
            {
                "lng":6.83590874047814,
                "lat":51.2763791801438
            },
            {
                "lng":6.8359379460466,
                "lat":51.2772068489247
            },
            {
                "lng":6.83434105450851,
                "lat":51.2768950052171
            },
            {
                "lng":6.83166011229513,
                "lat":51.2784019539367
            },
            {
                "lng":6.83109697535607,
                "lat":51.2783630098778
            },
            {
                "lng":6.83228864959341,
                "lat":51.2803683266783
            },
            {
                "lng":6.83057806820012,
                "lat":51.2805835919082
            },
            {
                "lng":6.82898575055399,
                "lat":51.279890257684
            },
            {
                "lng":6.82830662325404,
                "lat":51.2791514353303
            },
            {
                "lng":6.82493431894254,
                "lat":51.273598292774
            },
            {
                "lng":6.82173150022879,
                "lat":51.2739381234376
            },
            {
                "lng":6.81870840855229,
                "lat":51.2745084821395
            },
            {
                "lng":6.81643093124683,
                "lat":51.2753519595444
            },
            {
                "lng":6.81492098053143,
                "lat":51.2760401086751
            },
            {
                "lng":6.81262294043406,
                "lat":51.2773947685443
            },
            {
                "lng":6.80968782664374,
                "lat":51.2796440067917
            },
            {
                "lng":6.80731573124259,
                "lat":51.2791021585624
            },
            {
                "lng":6.80351733494512,
                "lat":51.2789872238735
            },
            {
                "lng":6.80305509707008,
                "lat":51.2796828288317
            },
            {
                "lng":6.80348587368212,
                "lat":51.2804670535424
            },
            {
                "lng":6.80399277923091,
                "lat":51.2822619552136
            },
            {
                "lng":6.80386947436917,
                "lat":51.2870674732766
            },
            {
                "lng":6.79950754029011,
                "lat":51.2896122757413
            },
            {
                "lng":6.79781589592693,
                "lat":51.2903263799376
            },
            {
                "lng":6.79656211668904,
                "lat":51.2910281986802
            },
            {
                "lng":6.79532596504526,
                "lat":51.2911158106302
            },
            {
                "lng":6.79417549958843,
                "lat":51.2905259253759
            },
            {
                "lng":6.79335676269848,
                "lat":51.2904067974526
            },
            {
                "lng":6.79294414909787,
                "lat":51.2909861133466
            },
            {
                "lng":6.79159770404176,
                "lat":51.2908881386993
            },
            {
                "lng":6.79121481262845,
                "lat":51.2921236356341
            },
            {
                "lng":6.78653114651072,
                "lat":51.2920043976523
            },
            {
                "lng":6.78675176531486,
                "lat":51.2904474766028
            },
            {
                "lng":6.78664712335114,
                "lat":51.2893994627509
            },
            {
                "lng":6.78068276201067,
                "lat":51.2865622934787
            },
            {
                "lng":6.78043184600886,
                "lat":51.2865667986435
            },
            {
                "lng":6.77480633356792,
                "lat":51.2838612988447
            },
            {
                "lng":6.77630329108795,
                "lat":51.2814177882054
            },
            {
                "lng":6.77329628063952,
                "lat":51.2812836306612
            },
            {
                "lng":6.77365632962893,
                "lat":51.2803267328412
            },
            {
                "lng":6.76924967103116,
                "lat":51.2797159794472
            },
            {
                "lng":6.76898977778787,
                "lat":51.279199292565
            },
            {
                "lng":6.76937799222797,
                "lat":51.2786717563837
            },
            {
                "lng":6.76660205713093,
                "lat":51.2753746598041
            },
            {
                "lng":6.76500066002429,
                "lat":51.2744130743377
            },
            {
                "lng":6.76296794721168,
                "lat":51.2736069051281
            },
            {
                "lng":6.76264846045925,
                "lat":51.2729584772571
            },
            {
                "lng":6.75979234332299,
                "lat":51.272950064924
            },
            {
                "lng":6.7603335697795,
                "lat":51.2714119118287
            },
            {
                "lng":6.75997113037668,
                "lat":51.2703448127552
            },
            {
                "lng":6.76144706475619,
                "lat":51.2657244581264
            },
            {
                "lng":6.76190553740107,
                "lat":51.265213668919
            },
            {
                "lng":6.76302908682557,
                "lat":51.2617201933984
            },
            {
                "lng":6.76241220712853,
                "lat":51.260626921096
            },
            {
                "lng":6.76304519064086,
                "lat":51.2592190271304
            },
            {
                "lng":6.76353992447435,
                "lat":51.2593177002577
            },
            {
                "lng":6.76934908243726,
                "lat":51.2614154449397
            },
            {
                "lng":6.77159728094281,
                "lat":51.262031350332
            },
            {
                "lng":6.7724455619565,
                "lat":51.2624706486853
            },
            {
                "lng":6.77394598287902,
                "lat":51.2627578561512
            },
            {
                "lng":6.77749774292087,
                "lat":51.2627415483667
            },
            {
                "lng":6.77934270211221,
                "lat":51.2629952981804
            },
            {
                "lng":6.78617038458998,
                "lat":51.2631637901492
            },
            {
                "lng":6.79131738261298,
                "lat":51.2627039912921
            },
            {
                "lng":6.79286123711783,
                "lat":51.2574262125499
            },
            {
                "lng":6.79349491948628,
                "lat":51.2529844696093
            },
            {
                "lng":6.79597688966732,
                "lat":51.2524893858761
            },
            {
                "lng":6.79859617074088,
                "lat":51.2517138064094
            },
            {
                "lng":6.80162088903261,
                "lat":51.2505454844253
            },
            {
                "lng":6.80248489749072,
                "lat":51.2500675194632
            },
            {
                "lng":6.8143711625967,
                "lat":51.2430171733706
            },
            {
                "lng":6.82100011558947,
                "lat":51.2453466585076
            },
            {
                "lng":6.82196249917379,
                "lat":51.2456156764586
            },
            {
                "lng":6.82216198766033,
                "lat":51.2509522760855
            },
            {
                "lng":6.8248255424577,
                "lat":51.2516136498411
            },
            {
                "lng":6.82977916441466,
                "lat":51.252585375586
            },
            {
                "lng":6.83217683913815,
                "lat":51.253230316984
            },
            {
                "lng":6.83510132934842,
                "lat":51.254700666597
            },
            {
                "lng":6.83660037413999,
                "lat":51.254497888136
            },
            {
                "lng":6.83623543646896,
                "lat":51.2535619327881
            },
            {
                "lng":6.84656810171336,
                "lat":51.2562851987918
            },
            {
                "lng":6.84733582936395,
                "lat":51.2562650596338
            },
            {
                "lng":6.85015197354834,
                "lat":51.2551969656146
            },
            {
                "lng":6.85137758677303,
                "lat":51.2556717584409
            },
            {
                "lng":6.85115449663619,
                "lat":51.2562758003333
            },
            {
                "lng":6.85021886868405,
                "lat":51.2568626164275
            },
            {
                "lng":6.85532889308733,
                "lat":51.2582910144772
            },
            {
                "lng":6.8568353324478,
                "lat":51.2596089960137
            },
            {
                "lng":6.85730031787994,
                "lat":51.2602159358234
            },
            {
                "lng":6.85693384862417,
                "lat":51.2616200284997
            },
            {
                "lng":6.85789795702672,
                "lat":51.2626126611231
            },
            {
                "lng":6.85796647738601,
                "lat":51.2635682106165
            },
            {
                "lng":6.8589417477339,
                "lat":51.2638810435204
            },
            {
                "lng":6.86135913166646,
                "lat":51.2635700060019
            },
            {
                "lng":6.86248523609078,
                "lat":51.2637899653335
            },
            {
                "lng":6.86436248850811,
                "lat":51.2645542374978
            },
            {
                "lng":6.86640880900054,
                "lat":51.2651793753424
            },
            {
                "lng":6.86573920588909,
                "lat":51.2681803265972
            },
            {
                "lng":6.86738760257137,
                "lat":51.268442857568
            }
        ]

 }