{"Bezirk_01": {"2020": {"food": 139966, "water": 66.65, "ratio_vulnerable_age": 28.6, "population": 85936, "pop_density": 7605, "mean_household_size": 1.61}, "2021": {"food": 141273, "water": 67.27, "ratio_vulnerable_age": 28.6, "population": 86738, "pop_density": 7676, "mean_household_size": 1.61}, "2022": {"food": 142229, "water": 67.73, "ratio_vulnerable_age": 28.6, "population": 87325, "pop_density": 7727, "mean_household_size": 1.61}, "2023": {"food": 143185, "water": 68.18, "ratio_vulnerable_age": 28.6, "population": 87912, "pop_density": 7779, "mean_household_size": 1.61}, "2024": {"food": 144141, "water": 68.64, "ratio_vulnerable_age": 28.6, "population": 88499, "pop_density": 7831, "mean_household_size": 1.61}, "2025": {"food": 144880, "water": 68.99, "ratio_vulnerable_age": 28.6, "population": 88953, "pop_density": 7872, "mean_household_size": 1.61}, "2026": {"food": 145618, "water": 69.34, "ratio_vulnerable_age": 28.6, "population": 89406, "pop_density": 7912, "mean_household_size": 1.61}, "2027": {"food": 146422, "water": 69.72, "ratio_vulnerable_age": 28.6, "population": 89900, "pop_density": 7955, "mean_household_size": 1.61}, "2028": {"food": 147226, "water": 70.11, "ratio_vulnerable_age": 28.6, "population": 90393, "pop_density": 7999, "mean_household_size": 1.61}, "2029": {"food": 148008, "water": 70.48, "ratio_vulnerable_age": 28.6, "population": 90873, "pop_density": 8041, "mean_household_size": 1.61}, "2030": {"food": 148812, "water": 70.86, "ratio_vulnerable_age": 28.6, "population": 91367, "pop_density": 8085, "mean_household_size": 1.61}, "2031": {"food": 149615, "water": 71.25, "ratio_vulnerable_age": 28.6, "population": 91860, "pop_density": 8129, "mean_household_size": 1.61}, "2032": {"food": 150398, "water": 71.62, "ratio_vulnerable_age": 28.6, "population": 92341, "pop_density": 8171, "mean_household_size": 1.61}, "2033": {"food": 151136, "water": 71.97, "ratio_vulnerable_age": 28.6, "population": 92794, "pop_density": 8211, "mean_household_size": 1.61}, "2034": {"food": 151875, "water": 72.32, "ratio_vulnerable_age": 28.6, "population": 93248, "pop_density": 8252, "mean_household_size": 1.61}, "2035": {"food": 152613, "water": 72.67, "ratio_vulnerable_age": 28.6, "population": 93701, "pop_density": 8292, "mean_household_size": 1.61}}, "Bezirk_02": {"2020": {"food": 103333, "water": 49.21, "ratio_vulnerable_age": 31.8, "population": 64183, "pop_density": 8877, "mean_household_size": 1.76}, "2021": {"food": 104298, "water": 49.67, "ratio_vulnerable_age": 31.8, "population": 64782, "pop_density": 8959, "mean_household_size": 1.76}, "2022": {"food": 105004, "water": 50.01, "ratio_vulnerable_age": 31.8, "population": 65221, "pop_density": 9020, "mean_household_size": 1.76}, "2023": {"food": 105709, "water": 50.34, "ratio_vulnerable_age": 31.8, "population": 65659, "pop_density": 9081, "mean_household_size": 1.76}, "2024": {"food": 106415, "water": 50.68, "ratio_vulnerable_age": 31.8, "population": 66097, "pop_density": 9141, "mean_household_size": 1.76}, "2025": {"food": 106960, "water": 50.94, "ratio_vulnerable_age": 31.8, "population": 66436, "pop_density": 9188, "mean_household_size": 1.76}, "2026": {"food": 107506, "water": 51.2, "ratio_vulnerable_age": 31.8, "population": 66775, "pop_density": 9235, "mean_household_size": 1.76}, "2027": {"food": 108099, "water": 51.48, "ratio_vulnerable_age": 31.8, "population": 67143, "pop_density": 9286, "mean_household_size": 1.76}, "2028": {"food": 108693, "water": 51.76, "ratio_vulnerable_age": 31.8, "population": 67512, "pop_density": 9337, "mean_household_size": 1.76}, "2029": {"food": 109270, "water": 52.04, "ratio_vulnerable_age": 31.8, "population": 67870, "pop_density": 9387, "mean_household_size": 1.76}, "2030": {"food": 109863, "water": 52.32, "ratio_vulnerable_age": 31.8, "population": 68239, "pop_density": 9438, "mean_household_size": 1.76}, "2031": {"food": 110457, "water": 52.6, "ratio_vulnerable_age": 31.8, "population": 68608, "pop_density": 9489, "mean_household_size": 1.76}, "2032": {"food": 111034, "water": 52.88, "ratio_vulnerable_age": 31.8, "population": 68966, "pop_density": 9538, "mean_household_size": 1.76}, "2033": {"food": 111580, "water": 53.14, "ratio_vulnerable_age": 31.8, "population": 69305, "pop_density": 9585, "mean_household_size": 1.76}, "2034": {"food": 112125, "water": 53.4, "ratio_vulnerable_age": 31.8, "population": 69644, "pop_density": 9632, "mean_household_size": 1.76}, "2035": {"food": 112670, "water": 53.66, "ratio_vulnerable_age": 31.8, "population": 69982, "pop_density": 9679, "mean_household_size": 1.76}}, "Bezirk_03": {"2020": {"food": 197557, "water": 94.07, "ratio_vulnerable_age": 27.8, "population": 120994, "pop_density": 4883, "mean_household_size": 1.66}, "2021": {"food": 199402, "water": 94.95, "ratio_vulnerable_age": 27.8, "population": 122124, "pop_density": 4928, "mean_household_size": 1.66}, "2022": {"food": 200752, "water": 95.59, "ratio_vulnerable_age": 27.8, "population": 122950, "pop_density": 4961, "mean_household_size": 1.66}, "2023": {"food": 202101, "water": 96.23, "ratio_vulnerable_age": 27.8, "population": 123777, "pop_density": 4995, "mean_household_size": 1.66}, "2024": {"food": 203450, "water": 96.88, "ratio_vulnerable_age": 27.8, "population": 124603, "pop_density": 5028, "mean_household_size": 1.66}, "2025": {"food": 204493, "water": 97.37, "ratio_vulnerable_age": 27.8, "population": 125241, "pop_density": 5054, "mean_household_size": 1.66}, "2026": {"food": 205535, "water": 97.87, "ratio_vulnerable_age": 27.8, "population": 125880, "pop_density": 5080, "mean_household_size": 1.66}, "2027": {"food": 206670, "water": 98.41, "ratio_vulnerable_age": 27.8, "population": 126575, "pop_density": 5108, "mean_household_size": 1.66}, "2028": {"food": 207804, "water": 98.95, "ratio_vulnerable_age": 27.8, "population": 127270, "pop_density": 5136, "mean_household_size": 1.66}, "2029": {"food": 208908, "water": 99.48, "ratio_vulnerable_age": 27.8, "population": 127946, "pop_density": 5163, "mean_household_size": 1.66}, "2030": {"food": 210043, "water": 100.02, "ratio_vulnerable_age": 27.8, "population": 128641, "pop_density": 5191, "mean_household_size": 1.66}, "2031": {"food": 211177, "water": 100.56, "ratio_vulnerable_age": 27.8, "population": 129335, "pop_density": 5219, "mean_household_size": 1.66}, "2032": {"food": 212281, "water": 101.08, "ratio_vulnerable_age": 27.8, "population": 130012, "pop_density": 5246, "mean_household_size": 1.66}, "2033": {"food": 213324, "water": 101.58, "ratio_vulnerable_age": 27.8, "population": 130650, "pop_density": 5272, "mean_household_size": 1.66}, "2034": {"food": 214366, "water": 102.07, "ratio_vulnerable_age": 27.8, "population": 131289, "pop_density": 5298, "mean_household_size": 1.66}, "2035": {"food": 215409, "water": 102.57, "ratio_vulnerable_age": 27.8, "population": 131927, "pop_density": 5324, "mean_household_size": 1.66}}, "Bezirk_04": {"2020": {"food": 71330, "water": 33.97, "ratio_vulnerable_age": 38.1, "population": 45039, "pop_density": 3552, "mean_household_size": 1.91}, "2021": {"food": 71996, "water": 34.29, "ratio_vulnerable_age": 38.1, "population": 45459, "pop_density": 3585, "mean_household_size": 1.91}, "2022": {"food": 72483, "water": 34.52, "ratio_vulnerable_age": 38.1, "population": 45767, "pop_density": 3609, "mean_household_size": 1.91}, "2023": {"food": 72970, "water": 34.75, "ratio_vulnerable_age": 38.1, "population": 46075, "pop_density": 3633, "mean_household_size": 1.91}, "2024": {"food": 73457, "water": 34.98, "ratio_vulnerable_age": 38.1, "population": 46382, "pop_density": 3657, "mean_household_size": 1.91}, "2025": {"food": 73834, "water": 35.16, "ratio_vulnerable_age": 38.1, "population": 46620, "pop_density": 3676, "mean_household_size": 1.91}, "2026": {"food": 74210, "water": 35.34, "ratio_vulnerable_age": 38.1, "population": 46857, "pop_density": 3695, "mean_household_size": 1.91}, "2027": {"food": 74620, "water": 35.54, "ratio_vulnerable_age": 38.1, "population": 47116, "pop_density": 3715, "mean_household_size": 1.91}, "2028": {"food": 75030, "water": 35.73, "ratio_vulnerable_age": 38.1, "population": 47375, "pop_density": 3736, "mean_household_size": 1.91}, "2029": {"food": 75428, "water": 35.92, "ratio_vulnerable_age": 38.1, "population": 47626, "pop_density": 3756, "mean_household_size": 1.91}, "2030": {"food": 75838, "water": 36.12, "ratio_vulnerable_age": 38.1, "population": 47885, "pop_density": 3776, "mean_household_size": 1.91}, "2031": {"food": 76247, "water": 36.31, "ratio_vulnerable_age": 38.1, "population": 48144, "pop_density": 3796, "mean_household_size": 1.91}, "2032": {"food": 76646, "water": 36.5, "ratio_vulnerable_age": 38.1, "population": 48395, "pop_density": 3816, "mean_household_size": 1.91}, "2033": {"food": 77022, "water": 36.68, "ratio_vulnerable_age": 38.1, "population": 48633, "pop_density": 3835, "mean_household_size": 1.91}, "2034": {"food": 77399, "water": 36.86, "ratio_vulnerable_age": 38.1, "population": 48871, "pop_density": 3854, "mean_household_size": 1.91}, "2035": {"food": 77775, "water": 37.04, "ratio_vulnerable_age": 38.1, "population": 49108, "pop_density": 3872, "mean_household_size": 1.91}}, "Bezirk_05": {"2020": {"food": 54575, "water": 25.99, "ratio_vulnerable_age": 41.8, "population": 34534, "pop_density": 678, "mean_household_size": 2.17}, "2021": {"food": 55084, "water": 26.23, "ratio_vulnerable_age": 41.8, "population": 34856, "pop_density": 684, "mean_household_size": 2.17}, "2022": {"food": 55457, "water": 26.41, "ratio_vulnerable_age": 41.8, "population": 35092, "pop_density": 688, "mean_household_size": 2.17}, "2023": {"food": 55830, "water": 26.59, "ratio_vulnerable_age": 41.8, "population": 35328, "pop_density": 693, "mean_household_size": 2.17}, "2024": {"food": 56203, "water": 26.77, "ratio_vulnerable_age": 41.8, "population": 35564, "pop_density": 698, "mean_household_size": 2.17}, "2025": {"food": 56491, "water": 26.9, "ratio_vulnerable_age": 41.8, "population": 35746, "pop_density": 701, "mean_household_size": 2.17}, "2026": {"food": 56779, "water": 27.04, "ratio_vulnerable_age": 41.8, "population": 35928, "pop_density": 705, "mean_household_size": 2.17}, "2027": {"food": 57092, "water": 27.19, "ratio_vulnerable_age": 41.8, "population": 36127, "pop_density": 709, "mean_household_size": 2.17}, "2028": {"food": 57405, "water": 27.34, "ratio_vulnerable_age": 41.8, "population": 36325, "pop_density": 713, "mean_household_size": 2.17}, "2029": {"food": 57710, "water": 27.48, "ratio_vulnerable_age": 41.8, "population": 36518, "pop_density": 716, "mean_household_size": 2.17}, "2030": {"food": 58024, "water": 27.63, "ratio_vulnerable_age": 41.8, "population": 36716, "pop_density": 720, "mean_household_size": 2.17}, "2031": {"food": 58337, "water": 27.78, "ratio_vulnerable_age": 41.8, "population": 36914, "pop_density": 724, "mean_household_size": 2.17}, "2032": {"food": 58642, "water": 27.93, "ratio_vulnerable_age": 41.8, "population": 37107, "pop_density": 728, "mean_household_size": 2.17}, "2033": {"food": 58930, "water": 28.06, "ratio_vulnerable_age": 41.8, "population": 37290, "pop_density": 732, "mean_household_size": 2.17}, "2034": {"food": 59218, "water": 28.2, "ratio_vulnerable_age": 41.8, "population": 37472, "pop_density": 735, "mean_household_size": 2.17}, "2035": {"food": 59506, "water": 28.34, "ratio_vulnerable_age": 41.8, "population": 37654, "pop_density": 739, "mean_household_size": 2.17}}, "Bezirk_06": {"2020": {"food": 106179, "water": 50.56, "ratio_vulnerable_age": 37.3, "population": 66610, "pop_density": 3386, "mean_household_size": 2.02}, "2021": {"food": 107171, "water": 51.03, "ratio_vulnerable_age": 37.3, "population": 67232, "pop_density": 3417, "mean_household_size": 2.02}, "2022": {"food": 107896, "water": 51.38, "ratio_vulnerable_age": 37.3, "population": 67687, "pop_density": 3440, "mean_household_size": 2.02}, "2023": {"food": 108621, "water": 51.72, "ratio_vulnerable_age": 37.3, "population": 68142, "pop_density": 3463, "mean_household_size": 2.02}, "2024": {"food": 109346, "water": 52.07, "ratio_vulnerable_age": 37.3, "population": 68597, "pop_density": 3487, "mean_household_size": 2.02}, "2025": {"food": 109906, "water": 52.34, "ratio_vulnerable_age": 37.3, "population": 68948, "pop_density": 3504, "mean_household_size": 2.02}, "2026": {"food": 110467, "water": 52.6, "ratio_vulnerable_age": 37.3, "population": 69300, "pop_density": 3522, "mean_household_size": 2.02}, "2027": {"food": 111076, "water": 52.89, "ratio_vulnerable_age": 37.3, "population": 69682, "pop_density": 3542, "mean_household_size": 2.02}, "2028": {"food": 111686, "water": 53.18, "ratio_vulnerable_age": 37.3, "population": 70065, "pop_density": 3561, "mean_household_size": 2.02}, "2029": {"food": 112279, "water": 53.47, "ratio_vulnerable_age": 37.3, "population": 70437, "pop_density": 3580, "mean_household_size": 2.02}, "2030": {"food": 112889, "water": 53.76, "ratio_vulnerable_age": 37.3, "population": 70819, "pop_density": 3600, "mean_household_size": 2.02}, "2031": {"food": 113499, "water": 54.05, "ratio_vulnerable_age": 37.3, "population": 71202, "pop_density": 3619, "mean_household_size": 2.02}, "2032": {"food": 114092, "water": 54.33, "ratio_vulnerable_age": 37.3, "population": 71574, "pop_density": 3638, "mean_household_size": 2.02}, "2033": {"food": 114653, "water": 54.6, "ratio_vulnerable_age": 37.3, "population": 71926, "pop_density": 3656, "mean_household_size": 2.02}, "2034": {"food": 115213, "water": 54.86, "ratio_vulnerable_age": 37.3, "population": 72277, "pop_density": 3674, "mean_household_size": 2.02}, "2035": {"food": 115773, "water": 55.13, "ratio_vulnerable_age": 37.3, "population": 72629, "pop_density": 3691, "mean_household_size": 2.02}}, "Bezirk_07": {"2020": {"food": 74568, "water": 35.51, "ratio_vulnerable_age": 39.1, "population": 47072, "pop_density": 1697, "mean_household_size": 2.01}, "2021": {"food": 75264, "water": 35.84, "ratio_vulnerable_age": 39.1, "population": 47511, "pop_density": 1712, "mean_household_size": 2.01}, "2022": {"food": 75773, "water": 36.08, "ratio_vulnerable_age": 39.1, "population": 47833, "pop_density": 1724, "mean_household_size": 2.01}, "2023": {"food": 76283, "water": 36.33, "ratio_vulnerable_age": 39.1, "population": 48154, "pop_density": 1736, "mean_household_size": 2.01}, "2024": {"food": 76792, "water": 36.57, "ratio_vulnerable_age": 39.1, "population": 48476, "pop_density": 1747, "mean_household_size": 2.01}, "2025": {"food": 77186, "water": 36.76, "ratio_vulnerable_age": 39.1, "population": 48724, "pop_density": 1756, "mean_household_size": 2.01}, "2026": {"food": 77579, "water": 36.94, "ratio_vulnerable_age": 39.1, "population": 48973, "pop_density": 1765, "mean_household_size": 2.01}, "2027": {"food": 78007, "water": 37.15, "ratio_vulnerable_age": 39.1, "population": 49243, "pop_density": 1775, "mean_household_size": 2.01}, "2028": {"food": 78435, "water": 37.35, "ratio_vulnerable_age": 39.1, "population": 49513, "pop_density": 1785, "mean_household_size": 2.01}, "2029": {"food": 78852, "water": 37.55, "ratio_vulnerable_age": 39.1, "population": 49776, "pop_density": 1794, "mean_household_size": 2.01}, "2030": {"food": 79280, "water": 37.75, "ratio_vulnerable_age": 39.1, "population": 50047, "pop_density": 1804, "mean_household_size": 2.01}, "2031": {"food": 79709, "water": 37.96, "ratio_vulnerable_age": 39.1, "population": 50317, "pop_density": 1813, "mean_household_size": 2.01}, "2032": {"food": 80125, "water": 38.16, "ratio_vulnerable_age": 39.1, "population": 50580, "pop_density": 1823, "mean_household_size": 2.01}, "2033": {"food": 80519, "water": 38.34, "ratio_vulnerable_age": 39.1, "population": 50828, "pop_density": 1832, "mean_household_size": 2.01}, "2034": {"food": 80912, "water": 38.53, "ratio_vulnerable_age": 39.1, "population": 51077, "pop_density": 1841, "mean_household_size": 2.01}, "2035": {"food": 81306, "water": 38.72, "ratio_vulnerable_age": 39.1, "population": 51325, "pop_density": 1850, "mean_household_size": 2.01}}, "Bezirk_08": {"2020": {"food": 96868, "water": 46.13, "ratio_vulnerable_age": 37.8, "population": 60768, "pop_density": 2892, "mean_household_size": 2.0}, "2021": {"food": 97773, "water": 46.56, "ratio_vulnerable_age": 37.8, "population": 61335, "pop_density": 2919, "mean_household_size": 2.0}, "2022": {"food": 98434, "water": 46.88, "ratio_vulnerable_age": 37.8, "population": 61750, "pop_density": 2938, "mean_household_size": 2.0}, "2023": {"food": 99096, "water": 47.19, "ratio_vulnerable_age": 37.8, "population": 62165, "pop_density": 2958, "mean_household_size": 2.0}, "2024": {"food": 99757, "water": 47.51, "ratio_vulnerable_age": 37.8, "population": 62580, "pop_density": 2978, "mean_household_size": 2.0}, "2025": {"food": 100268, "water": 47.75, "ratio_vulnerable_age": 37.8, "population": 62901, "pop_density": 2993, "mean_household_size": 2.0}, "2026": {"food": 100780, "water": 47.99, "ratio_vulnerable_age": 37.8, "population": 63222, "pop_density": 3008, "mean_household_size": 2.0}, "2027": {"food": 101336, "water": 48.26, "ratio_vulnerable_age": 37.8, "population": 63571, "pop_density": 3025, "mean_household_size": 2.0}, "2028": {"food": 101892, "water": 48.52, "ratio_vulnerable_age": 37.8, "population": 63920, "pop_density": 3042, "mean_household_size": 2.0}, "2029": {"food": 102433, "water": 48.78, "ratio_vulnerable_age": 37.8, "population": 64259, "pop_density": 3058, "mean_household_size": 2.0}, "2030": {"food": 102990, "water": 49.05, "ratio_vulnerable_age": 37.8, "population": 64608, "pop_density": 3074, "mean_household_size": 2.0}, "2031": {"food": 103546, "water": 49.31, "ratio_vulnerable_age": 37.8, "population": 64957, "pop_density": 3091, "mean_household_size": 2.0}, "2032": {"food": 104087, "water": 49.57, "ratio_vulnerable_age": 37.8, "population": 65297, "pop_density": 3107, "mean_household_size": 2.0}, "2033": {"food": 104599, "water": 49.81, "ratio_vulnerable_age": 37.8, "population": 65617, "pop_density": 3122, "mean_household_size": 2.0}, "2034": {"food": 105110, "water": 50.06, "ratio_vulnerable_age": 37.8, "population": 65938, "pop_density": 3138, "mean_household_size": 2.0}, "2035": {"food": 105621, "water": 50.3, "ratio_vulnerable_age": 37.8, "population": 66259, "pop_density": 3153, "mean_household_size": 2.0}}, "Bezirk_09": {"2020": {"food": 150265, "water": 71.55, "ratio_vulnerable_age": 37.9, "population": 94359, "pop_density": 2575, "mean_household_size": 2.02}, "2021": {"food": 151669, "water": 72.22, "ratio_vulnerable_age": 37.9, "population": 95240, "pop_density": 2599, "mean_household_size": 2.02}, "2022": {"food": 152695, "water": 72.71, "ratio_vulnerable_age": 37.9, "population": 95885, "pop_density": 2616, "mean_household_size": 2.02}, "2023": {"food": 153721, "water": 73.2, "ratio_vulnerable_age": 37.9, "population": 96529, "pop_density": 2634, "mean_household_size": 2.02}, "2024": {"food": 154747, "water": 73.68, "ratio_vulnerable_age": 37.9, "population": 97173, "pop_density": 2651, "mean_household_size": 2.02}, "2025": {"food": 155540, "water": 74.06, "ratio_vulnerable_age": 37.9, "population": 97671, "pop_density": 2665, "mean_household_size": 2.02}, "2026": {"food": 156333, "water": 74.44, "ratio_vulnerable_age": 37.9, "population": 98169, "pop_density": 2678, "mean_household_size": 2.02}, "2027": {"food": 157196, "water": 74.85, "ratio_vulnerable_age": 37.9, "population": 98711, "pop_density": 2693, "mean_household_size": 2.02}, "2028": {"food": 158059, "water": 75.26, "ratio_vulnerable_age": 37.9, "population": 99253, "pop_density": 2708, "mean_household_size": 2.02}, "2029": {"food": 158899, "water": 75.66, "ratio_vulnerable_age": 37.9, "population": 99780, "pop_density": 2722, "mean_household_size": 2.02}, "2030": {"food": 159762, "water": 76.07, "ratio_vulnerable_age": 37.9, "population": 100322, "pop_density": 2737, "mean_household_size": 2.02}, "2031": {"food": 160625, "water": 76.48, "ratio_vulnerable_age": 37.9, "population": 100864, "pop_density": 2752, "mean_household_size": 2.02}, "2032": {"food": 161464, "water": 76.88, "ratio_vulnerable_age": 37.9, "population": 101391, "pop_density": 2766, "mean_household_size": 2.02}, "2033": {"food": 162257, "water": 77.26, "ratio_vulnerable_age": 37.9, "population": 101889, "pop_density": 2780, "mean_household_size": 2.02}, "2034": {"food": 163050, "water": 77.64, "ratio_vulnerable_age": 37.9, "population": 102387, "pop_density": 2794, "mean_household_size": 2.02}, "2035": {"food": 163843, "water": 78.02, "ratio_vulnerable_age": 37.9, "population": 102885, "pop_density": 2807, "mean_household_size": 2.02}}, "Bezirk_10": {"2020": {"food": 39060, "water": 18.6, "ratio_vulnerable_age": 41.8, "population": 24785, "pop_density": 4668, "mean_household_size": 2.22}, "2021": {"food": 39424, "water": 18.77, "ratio_vulnerable_age": 41.8, "population": 25016, "pop_density": 4711, "mean_household_size": 2.22}, "2022": {"food": 39691, "water": 18.9, "ratio_vulnerable_age": 41.8, "population": 25185, "pop_density": 4743, "mean_household_size": 2.22}, "2023": {"food": 39958, "water": 19.03, "ratio_vulnerable_age": 41.8, "population": 25355, "pop_density": 4775, "mean_household_size": 2.22}, "2024": {"food": 40225, "water": 19.15, "ratio_vulnerable_age": 41.8, "population": 25524, "pop_density": 4807, "mean_household_size": 2.22}, "2025": {"food": 40431, "water": 19.25, "ratio_vulnerable_age": 41.8, "population": 25655, "pop_density": 4831, "mean_household_size": 2.22}, "2026": {"food": 40637, "water": 19.35, "ratio_vulnerable_age": 41.8, "population": 25785, "pop_density": 4856, "mean_household_size": 2.22}, "2027": {"food": 40861, "water": 19.46, "ratio_vulnerable_age": 41.8, "population": 25928, "pop_density": 4883, "mean_household_size": 2.22}, "2028": {"food": 41086, "water": 19.56, "ratio_vulnerable_age": 41.8, "population": 26070, "pop_density": 4910, "mean_household_size": 2.22}, "2029": {"food": 41304, "water": 19.67, "ratio_vulnerable_age": 41.8, "population": 26209, "pop_density": 4936, "mean_household_size": 2.22}, "2030": {"food": 41528, "water": 19.78, "ratio_vulnerable_age": 41.8, "population": 26351, "pop_density": 4963, "mean_household_size": 2.22}, "2031": {"food": 41752, "water": 19.88, "ratio_vulnerable_age": 41.8, "population": 26493, "pop_density": 4989, "mean_household_size": 2.22}, "2032": {"food": 41971, "water": 19.99, "ratio_vulnerable_age": 41.8, "population": 26632, "pop_density": 5015, "mean_household_size": 2.22}, "2033": {"food": 42177, "water": 20.08, "ratio_vulnerable_age": 41.8, "population": 26763, "pop_density": 5040, "mean_household_size": 2.22}, "2034": {"food": 42383, "water": 20.18, "ratio_vulnerable_age": 41.8, "population": 26893, "pop_density": 5065, "mean_household_size": 2.22}, "2035": {"food": 42589, "water": 20.28, "ratio_vulnerable_age": 41.8, "population": 27024, "pop_density": 5089, "mean_household_size": 2.22}}}